MANIFEST.in
PluginFixedTitleUpdater.py
README.rst
setup.cfg
setup.py
scribes.editor.title_updater_fix.egg-info/PKG-INFO
scribes.editor.title_updater_fix.egg-info/SOURCES.txt
scribes.editor.title_updater_fix.egg-info/dependency_links.txt
scribes.editor.title_updater_fix.egg-info/not-zip-safe
scribes.editor.title_updater_fix.egg-info/top_level.txt