Metadata-Version: 1.0
Name: scribes.editor.title-updater-fix
Version: 0.2
Summary: Scribes plugin. Showes pretty names for python modules in editor titlebar
Home-page: http://github.com/baverman/scribes-goodies
Author: Anton Bobrov
Author-email: bobrov@vl.ru
License: UNKNOWN
Platform: UNKNOWN
